PCDTW/PCDTW.py
PCDTW/__init__.py
pcdtw-0.4.2.dist-info/METADATA
pcdtw-0.4.2.dist-info/WHEEL
pcdtw-0.4.2.dist-info/licenses/LICENSE.txt
pcdtw-0.4.2.dist-info/RECORD
