Metadata-Version: 2.4
Name: PCDTW
Version: 0.4.2
Summary: This package has functions for the conversion of amino acid sequences to physicochemical vectors and the subsequent analysis of those vector sequences.
Project-URL: Homepage, https://github.com/JamberFX/PCDTWPackage
Author-email: Jamie Dixson <realtorjamied@gmail.com>
License-Expression: MIT
License-File: LICENSE.txt
Classifier: License :: OSI Approved :: MIT License
Classifier: Operating System :: OS Independent
Classifier: Programming Language :: Python :: 3
Requires-Python: >=3.6
Requires-Dist: dtaidistance
Requires-Dist: numpy
Requires-Dist: pandas
